setup.py
pylocalnet/__init__.py
pylocalnet/pylocalnet.py
pylocalnet.egg-info/PKG-INFO
pylocalnet.egg-info/SOURCES.txt
pylocalnet.egg-info/dependency_links.txt
pylocalnet.egg-info/entry_points.txt
pylocalnet.egg-info/top_level.txt