Metadata-Version: 1.0
Name: pylocalnet
Version: 1.0.0
Summary: ARP reconnaissance tool POC
Home-page: UNKNOWN
Author: BrainDisassembly
Author-email: braindisassm@gmail.com
License: GPL v3
Platform: UNKNOWN
